odoo/addons/hr_expense_exception/README.rst
odoo/addons/hr_expense_exception/__init__.py
odoo/addons/hr_expense_exception/__manifest__.py
odoo/addons/hr_expense_exception/data/expense_sheet_exception_data.xml
odoo/addons/hr_expense_exception/i18n/hr_expense_exception.pot
odoo/addons/hr_expense_exception/models/__init__.py
odoo/addons/hr_expense_exception/models/exception_rule.py
odoo/addons/hr_expense_exception/models/hr_expense.py
odoo/addons/hr_expense_exception/models/hr_expense_sheet.py
odoo/addons/hr_expense_exception/readme/CONTRIBUTORS.rst
odoo/addons/hr_expense_exception/readme/DESCRIPTION.rst
odoo/addons/hr_expense_exception/security/ir.model.access.csv
odoo/addons/hr_expense_exception/static/description/icon.png
odoo/addons/hr_expense_exception/static/description/index.html
odoo/addons/hr_expense_exception/tests/__init__.py
odoo/addons/hr_expense_exception/tests/test_expense_sheet_exception.py
odoo/addons/hr_expense_exception/views/hr_expense_view.xml
odoo/addons/hr_expense_exception/wizard/__init__.py
odoo/addons/hr_expense_exception/wizard/expense_sheet_exception_confirm.py
odoo/addons/hr_expense_exception/wizard/expense_sheet_exception_confirm_view.xml
odoo14_addon_hr_expense_exception-14.0.1.0.1.dist-info/METADATA
odoo14_addon_hr_expense_exception-14.0.1.0.1.dist-info/WHEEL
odoo14_addon_hr_expense_exception-14.0.1.0.1.dist-info/top_level.txt
odoo14_addon_hr_expense_exception-14.0.1.0.1.dist-info/RECORD
